pythonlemmy/__init__.py
pythonlemmy/lemmyhttp.py
pythonlemmy/objects.py
pythonlemmy/request_controller.py
pythonlemmy/responses.py
pythonlemmy/types.py
pythonlemmy/utils.py
pythonlemmy/version.py
pythonlemmy/views.py
tests/__init__.py
tests/conftest.py
tests/integration/__init__.py
tests/integration/test_import.py
tests/integration/test_lemmyhttp.py
tests/unit/__init__.py
tests/unit/http/__init__.py
tests/unit/http/test_get_comment.py
tests/unit/http/test_get_federated_instances.py
tests/unit/http/test_login.py
tests/unit/http/test_set_jwt.py
type-generator/main.py
type-generator/headers/lemmyhttp_header.py
type-generator/headers/object_header.py
type-generator/headers/response_header.py
type-generator/headers/view_header.py
type-generator/src/__init__.py
type-generator/src/models.py
type-generator/src/util.py
type-generator/src/generator/__init__.py
type-generator/src/generator/http_generator.py
type-generator/src/generator/model_generator.py
type-generator/src/visitor/__init__.py
type-generator/src/visitor/enum_visitor.py
type-generator/src/visitor/http_visitor.py
type-generator/src/visitor/model_visitor.py
type-generator/src/visitor/visitor.py
pythonlemmy-0.3.0.dist-info/LICENSE
pythonlemmy-0.3.0.dist-info/METADATA
pythonlemmy-0.3.0.dist-info/WHEEL
pythonlemmy-0.3.0.dist-info/top_level.txt
pythonlemmy-0.3.0.dist-info/RECORD
