Metadata-Version: 2.1
Name: pythonlemmy
Version: 0.3.0
Summary: A Python package for accessing the LemmyHttp API
Author-email: Travis Kessler <travis.j.kessler@gmail.com>, Emily McLean <emily@mclean.lgbt>
Project-URL: Homepage, https://github.com/BenMMcLean/plemmy
Project-URL: Bug Tracker, https://github.com/BenMMcLean/plemmy/issues
Classifier: Programming Language :: Python :: 3.7
Classifier: License :: OSI Approved :: Apache Software License
Classifier: Operating System :: OS Independent
Requires-Python: >=3.7
License-File: LICENSE
Requires-Dist: requests
Requires-Dist: typing-extensions >=4.9.0
